code.py
fifteen_puzzle_adjam-0.0.12.dist-info/METADATA
fifteen_puzzle_adjam-0.0.12.dist-info/WHEEL
fifteen_puzzle_adjam-0.0.12.dist-info/entry_points.txt
fifteen_puzzle_adjam-0.0.12.dist-info/RECORD
